<annotation>
	<folder>P</folder>
	<filename>Pistol_208.jpg</filename>
	<path>C:\Users\Ashwani\Downloads\5000_1\5000_1\StockImages\P\Pistol_208.jpg</path>
	<source>
		<database>Unknown</database>
	</source>
	<size>
		<width>400</width>
		<height>242</height>
		<depth>3</depth>
	</size>
	<segmented>0</segmented>
	<object>
		<name>Guns</name>
		<pose>Unspecified</pose>
		<truncated>1</truncated>
		<difficult>0</difficult>
		<bndbox>
			<xmin>6</xmin>
			<ymin>4</ymin>
			<xmax>399</xmax>
			<ymax>242</ymax>
		</bndbox>
	</object>
</annotation>
